shadow_geeks/__init__.py
shadow_geeks/hello.py
shadow_geeks-1.0.0.dist-info/METADATA
shadow_geeks-1.0.0.dist-info/WHEEL
shadow_geeks-1.0.0.dist-info/top_level.txt
shadow_geeks-1.0.0.dist-info/RECORD
