Metadata-Version: 2.1
Name: shadow-geeks
Version: 1.0.0
Summary: A package created for team shadow geeks
Author: Rahul
Author-email: rockr3876@gmail.com
License: MIT
Requires-Dist: numpy
